openapp.py
mcp_openapp-0.1.0.dist-info/METADATA
mcp_openapp-0.1.0.dist-info/WHEEL
mcp_openapp-0.1.0.dist-info/top_level.txt
mcp_openapp-0.1.0.dist-info/RECORD
