Metadata-Version: 2.4
Name: mcp-openapp
Version: 0.1.0
Summary: open pc app with NL
Author-email: jiangcheng <503780146@qq.com>
Requires-Python: >=3.10
Requires-Dist: httpx>=0.28.1
Requires-Dist: mcp[cli]>=1.9.1
Requires-Dist: openai>=1.82.0
